License.txt
README.txt
setup.py
yt_calc/__init__.py
yt_calc.egg-info/PKG-INFO
yt_calc.egg-info/SOURCES.txt
yt_calc.egg-info/dependency_links.txt
yt_calc.egg-info/top_level.txt